[
  {
    "id": "communication-001",
    "category": "relationship_dynamics",
    "text": "Partnerime gerçekten ne demek istediğimi rahatça söyleyebiliyorum.",
    "answer_type": "likert",
    "scale_low_label": "kesinlikle katılmıyorum",
    "scale_high_label": "kesinlikle katılıyorum",
    "options": null,
    "depth": "deep",
    "weight": "revealing",
    "spice": 0,
    "language": "tr",
    "tags": ["communication", "trust"],
    "status": "draft",
    "created_at": "2026-05-24T00:00:00Z",
    "updated_at": "2026-05-24T00:00:00Z",
    "contributor": "ai-generated"
  },
  {
    "id": "communication-002",
    "category": "relationship_dynamics",
    "text": "Bir şeyleri içime atmaktansa hemen konuşup halletmeyi tercih ederim.",
    "answer_type": "likert",
    "scale_low_label": "kesinlikle katılmıyorum",
    "scale_high_label": "kesinlikle katılıyorum",
    "options": null,
    "depth": "light",
    "weight": "reflective",
    "spice": 0,
    "language": "tr",
    "tags": ["communication", "conflict"],
    "status": "draft",
    "created_at": "2026-05-24T00:00:00Z",
    "updated_at": "2026-05-24T00:00:00Z",
    "contributor": "ai-generated"
  },
  {
    "id": "communication-003",
    "category": "relationship_dynamics",
    "text": "Genelde partnerimin neye ihtiyacım olduğunu söylemeden anlamasını beklerim.",
    "answer_type": "likert",
    "scale_low_label": "kesinlikle katılmıyorum",
    "scale_high_label": "kesinlikle katılıyorum",
    "options": null,
    "depth": "deep",
    "weight": "revealing",
    "spice": 0,
    "language": "tr",
    "tags": ["communication", "feeling_hurt"],
    "status": "draft",
    "created_at": "2026-05-24T00:00:00Z",
    "updated_at": "2026-05-24T00:00:00Z",
    "contributor": "ai-generated"
  },
  {
    "id": "communication-004",
    "category": "relationship_dynamics",
    "text": "Konuşmaktan çok dinlemeyi beceririm.",
    "answer_type": "likert",
    "scale_low_label": "kesinlikle katılmıyorum",
    "scale_high_label": "kesinlikle katılıyorum",
    "options": null,
    "depth": "light",
    "weight": "reflective",
    "spice": 0,
    "language": "tr",
    "tags": ["communication", "self_perception"],
    "status": "draft",
    "created_at": "2026-05-24T00:00:00Z",
    "updated_at": "2026-05-24T00:00:00Z",
    "contributor": "ai-generated"
  },
  {
    "id": "communication-005",
    "category": "relationship_dynamics",
    "text": "Bir şey beni rahatsız ettiğinde biriktirmek yerine dile getiririm.",
    "answer_type": "likert",
    "scale_low_label": "kesinlikle katılmıyorum",
    "scale_high_label": "kesinlikle katılıyorum",
    "options": null,
    "depth": "deep",
    "weight": "revealing",
    "spice": 0,
    "language": "tr",
    "tags": ["communication", "conflict"],
    "status": "draft",
    "created_at": "2026-05-24T00:00:00Z",
    "updated_at": "2026-05-24T00:00:00Z",
    "contributor": "ai-generated"
  },
  {
    "id": "communication-006",
    "category": "relationship_dynamics",
    "text": "Çoğu zaman partnerim tarafından gerçekten duyulduğumu hissediyorum.",
    "answer_type": "likert",
    "scale_low_label": "kesinlikle katılmıyorum",
    "scale_high_label": "kesinlikle katılıyorum",
    "options": null,
    "depth": "deep",
    "weight": "revealing",
    "spice": 0,
    "language": "tr",
    "tags": ["communication", "feeling_loved"],
    "status": "draft",
    "created_at": "2026-05-24T00:00:00Z",
    "updated_at": "2026-05-24T00:00:00Z",
    "contributor": "ai-generated"
  },
  {
    "id": "communication-007",
    "category": "relationship_dynamics",
    "text": "Ortamı germemek için düşündüklerimi yumuşatma ya da kendime saklama eğilimindeyim.",
    "answer_type": "likert",
    "scale_low_label": "kesinlikle katılmıyorum",
    "scale_high_label": "kesinlikle katılıyorum",
    "options": null,
    "depth": "deep",
    "weight": "revealing",
    "spice": 0,
    "language": "tr",
    "tags": ["communication", "conflict"],
    "status": "draft",
    "created_at": "2026-05-24T00:00:00Z",
    "updated_at": "2026-05-24T00:00:00Z",
    "contributor": "ai-generated"
  },
  {
    "id": "communication-008",
    "category": "relationship_dynamics",
    "text": "Duygularımdan bahsetmek bana doğal geliyor.",
    "answer_type": "likert",
    "scale_low_label": "kesinlikle katılmıyorum",
    "scale_high_label": "kesinlikle katılıyorum",
    "options": null,
    "depth": "deep",
    "weight": "revealing",
    "spice": 0,
    "language": "tr",
    "tags": ["communication", "feelings"],
    "status": "draft",
    "created_at": "2026-05-24T00:00:00Z",
    "updated_at": "2026-05-24T00:00:00Z",
    "contributor": "ai-generated"
  },
  {
    "id": "communication-009",
    "category": "relationship_dynamics",
    "text": "Zor bir konuşmaya başlamadan önce düşüncelerimi toparlamak için zamana ihtiyacım var.",
    "answer_type": "likert",
    "scale_low_label": "kesinlikle katılmıyorum",
    "scale_high_label": "kesinlikle katılıyorum",
    "options": null,
    "depth": "light",
    "weight": "reflective",
    "spice": 0,
    "language": "tr",
    "tags": ["communication", "self_perception"],
    "status": "draft",
    "created_at": "2026-05-24T00:00:00Z",
    "updated_at": "2026-05-24T00:00:00Z",
    "contributor": "ai-generated"
  },
  {
    "id": "communication-010",
    "category": "relationship_dynamics",
    "text": "Tanıdığım çoğu çiftten daha iyi iletişim kuruyoruz.",
    "answer_type": "likert",
    "scale_low_label": "kesinlikle katılmıyorum",
    "scale_high_label": "kesinlikle katılıyorum",
    "options": null,
    "depth": "deep",
    "weight": "revealing",
    "spice": 0,
    "language": "tr",
    "tags": ["communication", "relationship_dynamics"],
    "status": "draft",
    "created_at": "2026-05-24T00:00:00Z",
    "updated_at": "2026-05-24T00:00:00Z",
    "contributor": "ai-generated"
  },
  {
    "id": "communication-011",
    "category": "relationship_dynamics",
    "text": "Doğal iletişim tarzım nasıl?",
    "answer_type": "multiple_choice",
    "scale_low_label": null,
    "scale_high_label": null,
    "options": [
      "Direkt ve açık",
      "Yumuşak ve dikkatli",
      "Düşünmek için zamana ihtiyacım var",
      "Zor konulardan kaçınırım",
      "Konuşmadan önce çok düşünürüm"
    ],
    "depth": "deep",
    "weight": "revealing",
    "spice": 0,
    "language": "tr",
    "tags": ["communication", "self_perception"],
    "status": "draft",
    "created_at": "2026-05-24T00:00:00Z",
    "updated_at": "2026-05-24T00:00:00Z",
    "contributor": "ai-generated"
  },
  {
    "id": "communication-012",
    "category": "relationship_dynamics",
    "text": "Üzgün olduğumda nasıl iletişim kurmayı tercih ederim?",
    "answer_type": "multiple_choice",
    "scale_low_label": null,
    "scale_high_label": null,
    "options": [
      "Hemen konuşurum",
      "Önce alan isterim",
      "Yazıya dökerim",
      "Sakinleşmeyi beklerim",
      "İma eder, anlaşılmasını umarım"
    ],
    "depth": "deep",
    "weight": "revealing",
    "spice": 0,
    "language": "tr",
    "tags": ["communication", "conflict"],
    "status": "draft",
    "created_at": "2026-05-24T00:00:00Z",
    "updated_at": "2026-05-24T00:00:00Z",
    "contributor": "ai-generated"
  },
  {
    "id": "communication-013",
    "category": "relationship_dynamics",
    "text": "Ciddi bir konuşma sırasında partnerimden en çok neye ihtiyacım var?",
    "answer_type": "multiple_choice",
    "scale_low_label": null,
    "scale_high_label": null,
    "options": ["Duyulduğumu hissetmek", "Sabır", "Dürüstlük", "Güven", "Çözüm"],
    "depth": "deep",
    "weight": "revealing",
    "spice": 0,
    "language": "tr",
    "tags": ["communication", "feeling_loved"],
    "status": "draft",
    "created_at": "2026-05-24T00:00:00Z",
    "updated_at": "2026-05-24T00:00:00Z",
    "contributor": "ai-generated"
  },
  {
    "id": "communication-014",
    "category": "relationship_dynamics",
    "text": "Aramızdaki iletişimi en çok ne sekteye uğratıyor?",
    "answer_type": "multiple_choice",
    "scale_low_label": null,
    "scale_high_label": null,
    "options": [
      "Sormak yerine varsaymak",
      "Yanlış zamanlama",
      "Savunmaya geçmek",
      "İçine atmak",
      "Birbirini anlamadan konuşmak"
    ],
    "depth": "deep",
    "weight": "revealing",
    "spice": 0,
    "language": "tr",
    "tags": ["communication", "conflict"],
    "status": "draft",
    "created_at": "2026-05-24T00:00:00Z",
    "updated_at": "2026-05-24T00:00:00Z",
    "contributor": "ai-generated"
  },
  {
    "id": "communication-015",
    "category": "relationship_dynamics",
    "text": "Zor konular için hangi iletişim biçimi bana en uygun geliyor?",
    "answer_type": "multiple_choice",
    "scale_low_label": null,
    "scale_high_label": null,
    "options": [
      "Yüz yüze",
      "Yan yana yürürken",
      "Yazılı olarak",
      "Telefonda",
      "Doğal olarak gelirse"
    ],
    "depth": "light",
    "weight": "reflective",
    "spice": 0,
    "language": "tr",
    "tags": ["communication", "self_perception"],
    "status": "draft",
    "created_at": "2026-05-24T00:00:00Z",
    "updated_at": "2026-05-24T00:00:00Z",
    "contributor": "ai-generated"
  },
  {
    "id": "communication-016",
    "category": "relationship_dynamics",
    "text": "İhtiyacım olan şeyi açıkça istemek bana kolay geliyor mu?",
    "answer_type": "binary",
    "scale_low_label": null,
    "scale_high_label": null,
    "options": ["Evet", "Hayır"],
    "depth": "deep",
    "weight": "revealing",
    "spice": 0,
    "language": "tr",
    "tags": ["communication", "boundaries"],
    "status": "draft",
    "created_at": "2026-05-24T00:00:00Z",
    "updated_at": "2026-05-24T00:00:00Z",
    "contributor": "ai-generated"
  },
  {
    "id": "communication-017",
    "category": "relationship_dynamics",
    "text": "Konuşma gerginleşince susma eğilimim var mı?",
    "answer_type": "binary",
    "scale_low_label": null,
    "scale_high_label": null,
    "options": ["Evet", "Hayır"],
    "depth": "deep",
    "weight": "revealing",
    "spice": 0,
    "language": "tr",
    "tags": ["communication", "conflict"],
    "status": "draft",
    "created_at": "2026-05-24T00:00:00Z",
    "updated_at": "2026-05-24T00:00:00Z",
    "contributor": "ai-generated"
  },
  {
    "id": "communication-018",
    "category": "relationship_dynamics",
    "text": "Gerçekten önemli olan şeyler hakkında yeterince konuştuğumuzu düşünüyor muyum?",
    "answer_type": "binary",
    "scale_low_label": null,
    "scale_high_label": null,
    "options": ["Evet", "Hayır"],
    "depth": "deep",
    "weight": "revealing",
    "spice": 0,
    "language": "tr",
    "tags": ["communication", "relationship_dynamics"],
    "status": "draft",
    "created_at": "2026-05-24T00:00:00Z",
    "updated_at": "2026-05-24T00:00:00Z",
    "contributor": "ai-generated"
  },
  {
    "id": "communication-019",
    "category": "relationship_dynamics",
    "text": "Söylenmesi zor bir şey olduğunda içimi dökmemi ne kolaylaştırır?",
    "answer_type": "free_text",
    "scale_low_label": null,
    "scale_high_label": null,
    "options": null,
    "depth": "deep",
    "weight": "revealing",
    "spice": 0,
    "language": "tr",
    "tags": ["communication", "trust"],
    "status": "draft",
    "created_at": "2026-05-24T00:00:00Z",
    "updated_at": "2026-05-24T00:00:00Z",
    "contributor": "ai-generated"
  },
  {
    "id": "communication-020",
    "category": "relationship_dynamics",
    "text": "Partnerim tarafından daha iyi anlaşıldığımı hissetmemi sağlayacak tek bir şey ne olurdu?",
    "answer_type": "free_text",
    "scale_low_label": null,
    "scale_high_label": null,
    "options": null,
    "depth": "deep",
    "weight": "revealing",
    "spice": 0,
    "language": "tr",
    "tags": ["communication", "feeling_loved"],
    "status": "draft",
    "created_at": "2026-05-24T00:00:00Z",
    "updated_at": "2026-05-24T00:00:00Z",
    "contributor": "ai-generated"
  },
  {
    "id": "conflict-001",
    "category": "relationship_dynamics",
    "text": "Çatışmadan kaçmak yerine doğrudan üstüne giderim.",
    "answer_type": "likert",
    "scale_low_label": "kesinlikle katılmıyorum",
    "scale_high_label": "kesinlikle katılıyorum",
    "options": null,
    "depth": "deep",
    "weight": "revealing",
    "spice": 0,
    "language": "tr",
    "tags": ["conflict", "self_perception"],
    "status": "draft",
    "created_at": "2026-05-24T00:00:00Z",
    "updated_at": "2026-05-24T00:00:00Z",
    "contributor": "ai-generated"
  },
  {
    "id": "conflict-002",
    "category": "relationship_dynamics",
    "text": "Bir tartışmayı çözmeden önce sakinleşmem gerekiyor.",
    "answer_type": "likert",
    "scale_low_label": "kesinlikle katılmıyorum",
    "scale_high_label": "kesinlikle katılıyorum",
    "options": null,
    "depth": "deep",
    "weight": "revealing",
    "spice": 0,
    "language": "tr",
    "tags": ["conflict", "coping"],
    "status": "draft",
    "created_at": "2026-05-24T00:00:00Z",
    "updated_at": "2026-05-24T00:00:00Z",
    "contributor": "ai-generated"
  },
  {
    "id": "conflict-003",
    "category": "relationship_dynamics",
    "text": "Bir kavganın ardından genelde ilk özür dileyen ben olurum.",
    "answer_type": "likert",
    "scale_low_label": "kesinlikle katılmıyorum",
    "scale_high_label": "kesinlikle katılıyorum",
    "options": null,
    "depth": "deep",
    "weight": "revealing",
    "spice": 0,
    "language": "tr",
    "tags": ["conflict", "self_perception"],
    "status": "draft",
    "created_at": "2026-05-24T00:00:00Z",
    "updated_at": "2026-05-24T00:00:00Z",
    "contributor": "ai-generated"
  },
  {
    "id": "conflict-004",
    "category": "relationship_dynamics",
    "text": "Yeni bir şey hakkında tartışırken eski meseleleri de gündeme getiririm.",
    "answer_type": "likert",
    "scale_low_label": "kesinlikle katılmıyorum",
    "scale_high_label": "kesinlikle katılıyorum",
    "options": null,
    "depth": "vulnerable",
    "weight": "revealing",
    "spice": 0,
    "language": "tr",
    "tags": ["conflict", "feeling_hurt"],
    "status": "draft",
    "created_at": "2026-05-24T00:00:00Z",
    "updated_at": "2026-05-24T00:00:00Z",
    "contributor": "ai-generated"
  },
  {
    "id": "conflict-005",
    "category": "relationship_dynamics",
    "text": "Haklı çıkmaktan çok meseleyi çözmek umurumda.",
    "answer_type": "likert",
    "scale_low_label": "kesinlikle katılmıyorum",
    "scale_high_label": "kesinlikle katılıyorum",
    "options": null,
    "depth": "deep",
    "weight": "revealing",
    "spice": 0,
    "language": "tr",
    "tags": ["conflict", "values"],
    "status": "draft",
    "created_at": "2026-05-24T00:00:00Z",
    "updated_at": "2026-05-24T00:00:00Z",
    "contributor": "ai-generated"
  },
  {
    "id": "conflict-006",
    "category": "relationship_dynamics",
    "text": "Tartışmada sesin yükselmesi beni gerçekten allak bullak ediyor.",
    "answer_type": "likert",
    "scale_low_label": "kesinlikle katılmıyorum",
    "scale_high_label": "kesinlikle katılıyorum",
    "options": null,
    "depth": "deep",
    "weight": "revealing",
    "spice": 0,
    "language": "tr",
    "tags": ["conflict", "feelings"],
    "status": "draft",
    "created_at": "2026-05-24T00:00:00Z",
    "updated_at": "2026-05-24T00:00:00Z",
    "contributor": "ai-generated"
  },
  {
    "id": "conflict-007",
    "category": "relationship_dynamics",
    "text": "Karşılık vermektense içime kapanma eğilimim var.",
    "answer_type": "likert",
    "scale_low_label": "kesinlikle katılmıyorum",
    "scale_high_label": "kesinlikle katılıyorum",
    "options": null,
    "depth": "deep",
    "weight": "revealing",
    "spice": 0,
    "language": "tr",
    "tags": ["conflict", "coping"],
    "status": "draft",
    "created_at": "2026-05-24T00:00:00Z",
    "updated_at": "2026-05-24T00:00:00Z",
    "contributor": "ai-generated"
  },
  {
    "id": "conflict-008",
    "category": "relationship_dynamics",
    "text": "Tartışmalardan genelde birbirimize daha yakın çıkarız.",
    "answer_type": "likert",
    "scale_low_label": "kesinlikle katılmıyorum",
    "scale_high_label": "kesinlikle katılıyorum",
    "options": null,
    "depth": "deep",
    "weight": "revealing",
    "spice": 0,
    "language": "tr",
    "tags": ["conflict", "relationship_dynamics"],
    "status": "draft",
    "created_at": "2026-05-24T00:00:00Z",
    "updated_at": "2026-05-24T00:00:00Z",
    "contributor": "ai-generated"
  },
  {
    "id": "conflict-009",
    "category": "relationship_dynamics",
    "text": "Bir tartışma çözüldükten sonra bile onu zihnimden atmakta zorlanırım.",
    "answer_type": "likert",
    "scale_low_label": "kesinlikle katılmıyorum",
    "scale_high_label": "kesinlikle katılıyorum",
    "options": null,
    "depth": "vulnerable",
    "weight": "revealing",
    "spice": 0,
    "language": "tr",
    "tags": ["conflict", "feeling_hurt"],
    "status": "draft",
    "created_at": "2026-05-24T00:00:00Z",
    "updated_at": "2026-05-24T00:00:00Z",
    "contributor": "ai-generated"
  },
  {
    "id": "conflict-010",
    "category": "relationship_dynamics",
    "text": "Ara sıra yaşanan çatışmaların ilişki için sağlıklı olduğunu düşünüyorum.",
    "answer_type": "likert",
    "scale_low_label": "kesinlikle katılmıyorum",
    "scale_high_label": "kesinlikle katılıyorum",
    "options": null,
    "depth": "light",
    "weight": "reflective",
    "spice": 0,
    "language": "tr",
    "tags": ["conflict", "values"],
    "status": "draft",
    "created_at": "2026-05-24T00:00:00Z",
    "updated_at": "2026-05-24T00:00:00Z",
    "contributor": "ai-generated"
  },
  {
    "id": "conflict-011",
    "category": "relationship_dynamics",
    "text": "Tartışmanın orta yerinde genelde nasıl tepki veririm?",
    "answer_type": "multiple_choice",
    "scale_low_label": null,
    "scale_high_label": null,
    "options": [
      "Hemen çözmeye çalışırım",
      "Uzaklaşmam gerekir",
      "Sessizleşirim",
      "Sesimi yükseltirim",
      "Hızla barış sağlamaya çalışırım"
    ],
    "depth": "deep",
    "weight": "revealing",
    "spice": 0,
    "language": "tr",
    "tags": ["conflict", "self_perception"],
    "status": "draft",
    "created_at": "2026-05-24T00:00:00Z",
    "updated_at": "2026-05-24T00:00:00Z",
    "contributor": "ai-generated"
  },
  {
    "id": "conflict-012",
    "category": "relationship_dynamics",
    "text": "En çok ne hakkında tartışıyoruz?",
    "answer_type": "multiple_choice",
    "scale_low_label": null,
    "scale_high_label": null,
    "options": [
      "Ev işleri ve düzen",
      "Para",
      "Vakit ve ilgi",
      "Aile veya arkadaşlar",
      "Günlük küçük şeyler"
    ],
    "depth": "deep",
    "weight": "revealing",
    "spice": 0,
    "language": "tr",
    "tags": ["conflict", "relationship_dynamics"],
    "status": "draft",
    "created_at": "2026-05-24T00:00:00Z",
    "updated_at": "2026-05-24T00:00:00Z",
    "contributor": "ai-generated"
  },
  {
    "id": "conflict-013",
    "category": "relationship_dynamics",
    "text": "Bir tartışmadan sonra bana en çok ne iyi gelir?",
    "answer_type": "multiple_choice",
    "scale_low_label": null,
    "scale_high_label": null,
    "options": [
      "Samimi bir özür",
      "Alan ve zaman",
      "Fiziksel bir teselli",
      "Konuyu sonuna kadar konuşmak",
      "Temiz bir sayfa açmak"
    ],
    "depth": "deep",
    "weight": "revealing",
    "spice": 0,
    "language": "tr",
    "tags": ["conflict", "feeling_loved"],
    "status": "draft",
    "created_at": "2026-05-24T00:00:00Z",
    "updated_at": "2026-05-24T00:00:00Z",
    "contributor": "ai-generated"
  },
  {
    "id": "conflict-014",
    "category": "relationship_dynamics",
    "text": "Bir tartışmanın gidişatında beni en çok ne yaralar?",
    "answer_type": "multiple_choice",
    "scale_low_label": null,
    "scale_high_label": null,
    "options": [
      "Önemsenmediğimi hissetmek",
      "Sert sözler",
      "Dışlanmak",
      "İşin kişiselleşmesi",
      "Duyulmadığımı hissetmek"
    ],
    "depth": "vulnerable",
    "weight": "revealing",
    "spice": 0,
    "language": "tr",
    "tags": ["conflict", "feeling_hurt"],
    "status": "draft",
    "created_at": "2026-05-24T00:00:00Z",
    "updated_at": "2026-05-24T00:00:00Z",
    "contributor": "ai-generated"
  },
  {
    "id": "conflict-015",
    "category": "relationship_dynamics",
    "text": "Kavgadan sonra genelde nasıl barışırım?",
    "answer_type": "multiple_choice",
    "scale_low_label": null,
    "scale_high_label": null,
    "options": [
      "Her şeyi konuşarak",
      "Bir sarılma veya sevgi göstererek",
      "Küçük bir jestle",
      "Espriyle havayı yumuşatarak",
      "Sessizce üstünü örterek"
    ],
    "depth": "deep",
    "weight": "revealing",
    "spice": 0,
    "language": "tr",
    "tags": ["conflict", "love_language"],
    "status": "draft",
    "created_at": "2026-05-24T00:00:00Z",
    "updated_at": "2026-05-24T00:00:00Z",
    "contributor": "ai-generated"
  },
  {
    "id": "conflict-016",
    "category": "relationship_dynamics",
    "text": "Çatışmada daha çok kavgacı mıyım yoksa kaçınan biri miyim?",
    "answer_type": "binary",
    "scale_low_label": null,
    "scale_high_label": null,
    "options": ["Kavgacı", "Kaçınan"],
    "depth": "deep",
    "weight": "revealing",
    "spice": 0,
    "language": "tr",
    "tags": ["conflict", "self_perception"],
    "status": "draft",
    "created_at": "2026-05-24T00:00:00Z",
    "updated_at": "2026-05-24T00:00:00Z",
    "contributor": "ai-generated"
  },
  {
    "id": "conflict-017",
    "category": "relationship_dynamics",
    "text": "Yanıldığımı kabul etmek bana kolay geliyor mu?",
    "answer_type": "binary",
    "scale_low_label": null,
    "scale_high_label": null,
    "options": ["Evet", "Hayır"],
    "depth": "deep",
    "weight": "revealing",
    "spice": 0,
    "language": "tr",
    "tags": ["conflict", "self_perception"],
    "status": "draft",
    "created_at": "2026-05-24T00:00:00Z",
    "updated_at": "2026-05-24T00:00:00Z",
    "contributor": "ai-generated"
  },
  {
    "id": "conflict-018",
    "category": "relationship_dynamics",
    "text": "Çift olarak çatışmayı iyi yönettiğimizi düşünüyor muyum?",
    "answer_type": "binary",
    "scale_low_label": null,
    "scale_high_label": null,
    "options": ["Evet", "Hayır"],
    "depth": "deep",
    "weight": "revealing",
    "spice": 0,
    "language": "tr",
    "tags": ["conflict", "relationship_dynamics"],
    "status": "draft",
    "created_at": "2026-05-24T00:00:00Z",
    "updated_at": "2026-05-24T00:00:00Z",
    "contributor": "ai-generated"
  },
  {
    "id": "conflict-019",
    "category": "relationship_dynamics",
    "text": "Daha kibar tartışmamıza yardımcı olacak tek bir şey ne olurdu?",
    "answer_type": "free_text",
    "scale_low_label": null,
    "scale_high_label": null,
    "options": null,
    "depth": "deep",
    "weight": "revealing",
    "spice": 0,
    "language": "tr",
    "tags": ["conflict", "communication"],
    "status": "draft",
    "created_at": "2026-05-24T00:00:00Z",
    "updated_at": "2026-05-24T00:00:00Z",
    "contributor": "ai-generated"
  },
  {
    "id": "conflict-020",
    "category": "relationship_dynamics",
    "text": "Ailemin çatışmayı yönetme biçiminden bu konuda ne öğrendim?",
    "answer_type": "free_text",
    "scale_low_label": null,
    "scale_high_label": null,
    "options": null,
    "depth": "vulnerable",
    "weight": "revealing",
    "spice": 0,
    "language": "tr",
    "tags": ["conflict", "family", "formative"],
    "status": "draft",
    "created_at": "2026-05-24T00:00:00Z",
    "updated_at": "2026-05-24T00:00:00Z",
    "contributor": "ai-generated"
  },
  {
    "id": "trust_jealousy-001",
    "category": "relationship_dynamics",
    "text": "Partnerime tamamen güveniyorum.",
    "answer_type": "likert",
    "scale_low_label": "kesinlikle katılmıyorum",
    "scale_high_label": "kesinlikle katılıyorum",
    "options": null,
    "depth": "deep",
    "weight": "revealing",
    "spice": 0,
    "language": "tr",
    "tags": ["trust_jealousy", "trust"],
    "status": "draft",
    "created_at": "2026-05-24T00:00:00Z",
    "updated_at": "2026-05-24T00:00:00Z",
    "contributor": "ai-generated"
  },
  {
    "id": "trust_jealousy-002",
    "category": "relationship_dynamics",
    "text": "İstediğimden daha kolay kıskanma eğilimim var.",
    "answer_type": "likert",
    "scale_low_label": "kesinlikle katılmıyorum",
    "scale_high_label": "kesinlikle katılıyorum",
    "options": null,
    "depth": "vulnerable",
    "weight": "revealing",
    "spice": 0,
    "language": "tr",
    "tags": ["trust_jealousy", "fears"],
    "status": "draft",
    "created_at": "2026-05-24T00:00:00Z",
    "updated_at": "2026-05-24T00:00:00Z",
    "contributor": "ai-generated"
  },
  {
    "id": "trust_jealousy-003",
    "category": "relationship_dynamics",
    "text": "Bir kez sarsılan güveni yeniden inşa etmek benim için çok zor.",
    "answer_type": "likert",
    "scale_low_label": "kesinlikle katılmıyorum",
    "scale_high_label": "kesinlikle katılıyorum",
    "options": null,
    "depth": "deep",
    "weight": "revealing",
    "spice": 0,
    "language": "tr",
    "tags": ["trust_jealousy", "trust"],
    "status": "draft",
    "created_at": "2026-05-24T00:00:00Z",
    "updated_at": "2026-05-24T00:00:00Z",
    "contributor": "ai-generated"
  },
  {
    "id": "trust_jealousy-004",
    "category": "relationship_dynamics",
    "text": "Partnerimin her cinsiyetten yakın arkadaşları olmasından rahatsız olmuyorum.",
    "answer_type": "likert",
    "scale_low_label": "kesinlikle katılmıyorum",
    "scale_high_label": "kesinlikle katılıyorum",
    "options": null,
    "depth": "deep",
    "weight": "revealing",
    "spice": 0,
    "language": "tr",
    "tags": ["trust_jealousy", "boundaries"],
    "status": "draft",
    "created_at": "2026-05-24T00:00:00Z",
    "updated_at": "2026-05-24T00:00:00Z",
    "contributor": "ai-generated"
  },
  {
    "id": "trust_jealousy-005",
    "category": "relationship_dynamics",
    "text": "Güven, kırılana kadar koşulsuz verilmesi gereken bir şeydir bence.",
    "answer_type": "likert",
    "scale_low_label": "kesinlikle katılmıyorum",
    "scale_high_label": "kesinlikle katılıyorum",
    "options": null,
    "depth": "deep",
    "weight": "revealing",
    "spice": 0,
    "language": "tr",
    "tags": ["trust_jealousy", "values"],
    "status": "draft",
    "created_at": "2026-05-24T00:00:00Z",
    "updated_at": "2026-05-24T00:00:00Z",
    "contributor": "ai-generated"
  },
  {
    "id": "trust_jealousy-006",
    "category": "relationship_dynamics",
    "text": "Hiçbir sorun olmasa bile bazen güvence almaya ihtiyacım oluyor.",
    "answer_type": "likert",
    "scale_low_label": "kesinlikle katılmıyorum",
    "scale_high_label": "kesinlikle katılıyorum",
    "options": null,
    "depth": "vulnerable",
    "weight": "revealing",
    "spice": 0,
    "language": "tr",
    "tags": ["trust_jealousy", "feeling_loved"],
    "status": "draft",
    "created_at": "2026-05-24T00:00:00Z",
    "updated_at": "2026-05-24T00:00:00Z",
    "contributor": "ai-generated"
  },
  {
    "id": "trust_jealousy-007",
    "category": "relationship_dynamics",
    "text": "Geçmişim, tam anlamıyla güvenmemi zorlaştırdı.",
    "answer_type": "likert",
    "scale_low_label": "kesinlikle katılmıyorum",
    "scale_high_label": "kesinlikle katılıyorum",
    "options": null,
    "depth": "vulnerable",
    "weight": "revealing",
    "spice": 0,
    "language": "tr",
    "tags": ["trust_jealousy", "past_relationships"],
    "status": "draft",
    "created_at": "2026-05-24T00:00:00Z",
    "updated_at": "2026-05-24T00:00:00Z",
    "contributor": "ai-generated"
  },
  {
    "id": "trust_jealousy-008",
    "category": "relationship_dynamics",
    "text": "Partnerimin çoğu zaman nerede olduğunu bilmek isterim.",
    "answer_type": "likert",
    "scale_low_label": "kesinlikle katılmıyorum",
    "scale_high_label": "kesinlikle katılıyorum",
    "options": null,
    "depth": "deep",
    "weight": "revealing",
    "spice": 0,
    "language": "tr",
    "tags": ["trust_jealousy", "boundaries"],
    "status": "draft",
    "created_at": "2026-05-24T00:00:00Z",
    "updated_at": "2026-05-24T00:00:00Z",
    "contributor": "ai-generated"
  },
  {
    "id": "trust_jealousy-009",
    "category": "relationship_dynamics",
    "text": "Bence azıcık kıskançlık, değer verildiğinin bir göstergesi.",
    "answer_type": "likert",
    "scale_low_label": "kesinlikle katılmıyorum",
    "scale_high_label": "kesinlikle katılıyorum",
    "options": null,
    "depth": "deep",
    "weight": "revealing",
    "spice": 0,
    "language": "tr",
    "tags": ["trust_jealousy", "values"],
    "status": "draft",
    "created_at": "2026-05-24T00:00:00Z",
    "updated_at": "2026-05-24T00:00:00Z",
    "contributor": "ai-generated"
  },
  {
    "id": "trust_jealousy-010",
    "category": "relationship_dynamics",
    "text": "Hayatımla ilgili partnerime karşı açık bir kitabım.",
    "answer_type": "likert",
    "scale_low_label": "kesinlikle katılmıyorum",
    "scale_high_label": "kesinlikle katılıyorum",
    "options": null,
    "depth": "deep",
    "weight": "revealing",
    "spice": 0,
    "language": "tr",
    "tags": ["trust_jealousy", "trust"],
    "status": "draft",
    "created_at": "2026-05-24T00:00:00Z",
    "updated_at": "2026-05-24T00:00:00Z",
    "contributor": "ai-generated"
  },
  {
    "id": "trust_jealousy-011",
    "category": "relationship_dynamics",
    "text": "Bende güveni en hızlı ne inşa eder?",
    "answer_type": "multiple_choice",
    "scale_low_label": null,
    "scale_high_label": null,
    "options": [
      "Zamanla tutarlılık",
      "Tam dürüstlük",
      "Sözünü tutmak",
      "Duygularda açıklık",
      "Önemli anlarda yanımda olmak"
    ],
    "depth": "deep",
    "weight": "revealing",
    "spice": 0,
    "language": "tr",
    "tags": ["trust_jealousy", "trust"],
    "status": "draft",
    "created_at": "2026-05-24T00:00:00Z",
    "updated_at": "2026-05-24T00:00:00Z",
    "contributor": "ai-generated"
  },
  {
    "id": "trust_jealousy-012",
    "category": "relationship_dynamics",
    "text": "Eğer kıskançlığım varsa, onu en çok ne tetikliyor?",
    "answer_type": "multiple_choice",
    "scale_low_label": null,
    "scale_high_label": null,
    "options": [
      "Başkalarından gelen ilgi",
      "Karşı cinsten yakın arkadaşlar",
      "Ayrı geçirilen zaman",
      "Saklı veya muğlak davranışlar",
      "Pek kıskanmam"
    ],
    "depth": "vulnerable",
    "weight": "revealing",
    "spice": 0,
    "language": "tr",
    "tags": ["trust_jealousy", "fears"],
    "status": "draft",
    "created_at": "2026-05-24T00:00:00Z",
    "updated_at": "2026-05-24T00:00:00Z",
    "contributor": "ai-generated"
  },
  {
    "id": "trust_jealousy-013",
    "category": "relationship_dynamics",
    "text": "Ani bir kıskançlık duygusuyla genelde nasıl başa çıkarım?",
    "answer_type": "multiple_choice",
    "scale_low_label": null,
    "scale_high_label": null,
    "options": [
      "Açıkça konuşurum",
      "Sessizce hissederim",
      "Güvence ararım",
      "Görmezden gelmeye çalışırım",
      "Pek nadir yaşarım"
    ],
    "depth": "vulnerable",
    "weight": "revealing",
    "spice": 0,
    "language": "tr",
    "tags": ["trust_jealousy", "coping"],
    "status": "draft",
    "created_at": "2026-05-24T00:00:00Z",
    "updated_at": "2026-05-24T00:00:00Z",
    "contributor": "ai-generated"
  },
  {
    "id": "trust_jealousy-014",
    "category": "relationship_dynamics",
    "text": "Bence partnerlerin birbirinden ne kadar mahremiyet alanı olmalı?",
    "answer_type": "multiple_choice",
    "scale_low_label": null,
    "scale_high_label": null,
    "options": [
      "Neredeyse hiç, tam açıklık",
      "Sağlıklı bir miktar",
      "Telefon ve mesajlar özel kalır",
      "Her birinin tercihine göre",
      "Pek düşünmedim"
    ],
    "depth": "deep",
    "weight": "revealing",
    "spice": 0,
    "language": "tr",
    "tags": ["trust_jealousy", "boundaries"],
    "status": "draft",
    "created_at": "2026-05-24T00:00:00Z",
    "updated_at": "2026-05-24T00:00:00Z",
    "contributor": "ai-generated"
  },
  {
    "id": "trust_jealousy-015",
    "category": "relationship_dynamics",
    "text": "Güvenime en çok ne zarar verir?",
    "answer_type": "multiple_choice",
    "scale_low_label": null,
    "scale_high_label": null,
    "options": [
      "Küçük bile olsa bir yalan",
      "Bir şeyleri saklamak",
      "Başkasıyla duygusal yakınlık",
      "Verilen sözü tutmamak",
      "Güvenilmez olmak"
    ],
    "depth": "deep",
    "weight": "revealing",
    "spice": 0,
    "language": "tr",
    "tags": ["trust_jealousy", "trust"],
    "status": "draft",
    "created_at": "2026-05-24T00:00:00Z",
    "updated_at": "2026-05-24T00:00:00Z",
    "contributor": "ai-generated"
  },
  {
    "id": "trust_jealousy-016",
    "category": "relationship_dynamics",
    "text": "Kendimi kıskanç biri olarak görüyor muyum?",
    "answer_type": "binary",
    "scale_low_label": null,
    "scale_high_label": null,
    "options": ["Evet", "Hayır"],
    "depth": "deep",
    "weight": "revealing",
    "spice": 0,
    "language": "tr",
    "tags": ["trust_jealousy", "self_perception"],
    "status": "draft",
    "created_at": "2026-05-24T00:00:00Z",
    "updated_at": "2026-05-24T00:00:00Z",
    "contributor": "ai-generated"
  },
  {
    "id": "trust_jealousy-017",
    "category": "relationship_dynamics",
    "text": "Bir ihanetten sonra güvenin tam olarak yeniden inşa edilebileceğine inanıyor muyum?",
    "answer_type": "binary",
    "scale_low_label": null,
    "scale_high_label": null,
    "options": ["Evet", "Hayır"],
    "depth": "deep",
    "weight": "revealing",
    "spice": 0,
    "language": "tr",
    "tags": ["trust_jealousy", "values"],
    "status": "draft",
    "created_at": "2026-05-24T00:00:00Z",
    "updated_at": "2026-05-24T00:00:00Z",
    "contributor": "ai-generated"
  },
  {
    "id": "trust_jealousy-018",
    "category": "relationship_dynamics",
    "text": "Genel olarak insanlara güvenmek bana kolay geliyor mu?",
    "answer_type": "binary",
    "scale_low_label": null,
    "scale_high_label": null,
    "options": ["Evet", "Hayır"],
    "depth": "deep",
    "weight": "revealing",
    "spice": 0,
    "language": "tr",
    "tags": ["trust_jealousy", "self_perception"],
    "status": "draft",
    "created_at": "2026-05-24T00:00:00Z",
    "updated_at": "2026-05-24T00:00:00Z",
    "contributor": "ai-generated"
  },
  {
    "id": "trust_jealousy-019",
    "category": "relationship_dynamics",
    "text": "İlişkide kendimi güvende hissetmek benim için nasıl görünür?",
    "answer_type": "free_text",
    "scale_low_label": null,
    "scale_high_label": null,
    "options": null,
    "depth": "deep",
    "weight": "revealing",
    "spice": 0,
    "language": "tr",
    "tags": ["trust_jealousy", "feeling_loved"],
    "status": "draft",
    "created_at": "2026-05-24T00:00:00Z",
    "updated_at": "2026-05-24T00:00:00Z",
    "contributor": "ai-generated"
  },
  {
    "id": "trust_jealousy-020",
    "category": "relationship_dynamics",
    "text": "Partnerimin kendimi daha güvende hissetmem için yapabileceği tek bir şey ne olurdu?",
    "answer_type": "free_text",
    "scale_low_label": null,
    "scale_high_label": null,
    "options": null,
    "depth": "vulnerable",
    "weight": "revealing",
    "spice": 0,
    "language": "tr",
    "tags": ["trust_jealousy", "communication", "feeling_loved"],
    "status": "draft",
    "created_at": "2026-05-24T00:00:00Z",
    "updated_at": "2026-05-24T00:00:00Z",
    "contributor": "ai-generated"
  },
  {
    "id": "boundaries-001",
    "category": "relationship_dynamics",
    "text": "Gerektiğinde sınır koymakta iyiyim.",
    "answer_type": "likert",
    "scale_low_label": "kesinlikle katılmıyorum",
    "scale_high_label": "kesinlikle katılıyorum",
    "options": null,
    "depth": "deep",
    "weight": "revealing",
    "spice": 0,
    "language": "tr",
    "tags": ["boundaries", "self_perception"],
    "status": "draft",
    "created_at": "2026-05-24T00:00:00Z",
    "updated_at": "2026-05-24T00:00:00Z",
    "contributor": "ai-generated"
  },
  {
    "id": "boundaries-002",
    "category": "relationship_dynamics",
    "text": "Yakın bir ilişkide bile düzenli olarak kendime ait zamana ihtiyacım var.",
    "answer_type": "likert",
    "scale_low_label": "kesinlikle katılmıyorum",
    "scale_high_label": "kesinlikle katılıyorum",
    "options": null,
    "depth": "light",
    "weight": "reflective",
    "spice": 0,
    "language": "tr",
    "tags": ["boundaries", "social_energy"],
    "status": "draft",
    "created_at": "2026-05-24T00:00:00Z",
    "updated_at": "2026-05-24T00:00:00Z",
    "contributor": "ai-generated"
  },
  {
    "id": "boundaries-003",
    "category": "relationship_dynamics",
    "text": "Aslında hayır demek istediğimde evet deme eğilimim var.",
    "answer_type": "likert",
    "scale_low_label": "kesinlikle katılmıyorum",
    "scale_high_label": "kesinlikle katılıyorum",
    "options": null,
    "depth": "vulnerable",
    "weight": "revealing",
    "spice": 0,
    "language": "tr",
    "tags": ["boundaries", "self_perception"],
    "status": "draft",
    "created_at": "2026-05-24T00:00:00Z",
    "updated_at": "2026-05-24T00:00:00Z",
    "contributor": "ai-generated"
  },
  {
    "id": "boundaries-004",
    "category": "relationship_dynamics",
    "text": "Tam olarak anlamasam bile başkalarının sınırlarına saygı duyarım.",
    "answer_type": "likert",
    "scale_low_label": "kesinlikle katılmıyorum",
    "scale_high_label": "kesinlikle katılıyorum",
    "options": null,
    "depth": "deep",
    "weight": "revealing",
    "spice": 0,
    "language": "tr",
    "tags": ["boundaries", "values"],
    "status": "draft",
    "created_at": "2026-05-24T00:00:00Z",
    "updated_at": "2026-05-24T00:00:00Z",
    "contributor": "ai-generated"
  },
  {
    "id": "boundaries-005",
    "category": "relationship_dynamics",
    "text": "Partnerimden ayrı zaman geçirmekten rahatsız olmam.",
    "answer_type": "likert",
    "scale_low_label": "kesinlikle katılmıyorum",
    "scale_high_label": "kesinlikle katılıyorum",
    "options": null,
    "depth": "light",
    "weight": "reflective",
    "spice": 0,
    "language": "tr",
    "tags": ["boundaries", "social_energy"],
    "status": "draft",
    "created_at": "2026-05-24T00:00:00Z",
    "updated_at": "2026-05-24T00:00:00Z",
    "contributor": "ai-generated"
  },
  {
    "id": "boundaries-006",
    "category": "relationship_dynamics",
    "text": "Kendi ihtiyaçlarımı önde tuttuğumda suçluluk duyuyorum.",
    "answer_type": "likert",
    "scale_low_label": "kesinlikle katılmıyorum",
    "scale_high_label": "kesinlikle katılıyorum",
    "options": null,
    "depth": "vulnerable",
    "weight": "revealing",
    "spice": 0,
    "language": "tr",
    "tags": ["boundaries", "feelings"],
    "status": "draft",
    "created_at": "2026-05-24T00:00:00Z",
    "updated_at": "2026-05-24T00:00:00Z",
    "contributor": "ai-generated"
  },
  {
    "id": "boundaries-007",
    "category": "relationship_dynamics",
    "text": "Hayatımın bazı kısımlarını sadece kendime saklarım.",
    "answer_type": "likert",
    "scale_low_label": "kesinlikle katılmıyorum",
    "scale_high_label": "kesinlikle katılıyorum",
    "options": null,
    "depth": "deep",
    "weight": "revealing",
    "spice": 0,
    "language": "tr",
    "tags": ["boundaries", "self_perception"],
    "status": "draft",
    "created_at": "2026-05-24T00:00:00Z",
    "updated_at": "2026-05-24T00:00:00Z",
    "contributor": "ai-generated"
  },
  {
    "id": "boundaries-008",
    "category": "relationship_dynamics",
    "text": "Partnerime onu hayal kırıklığına uğrattığımı hissetmeden hayır diyebiliyorum.",
    "answer_type": "likert",
    "scale_low_label": "kesinlikle katılmıyorum",
    "scale_high_label": "kesinlikle katılıyorum",
    "options": null,
    "depth": "deep",
    "weight": "revealing",
    "spice": 0,
    "language": "tr",
    "tags": ["boundaries", "communication"],
    "status": "draft",
    "created_at": "2026-05-24T00:00:00Z",
    "updated_at": "2026-05-24T00:00:00Z",
    "contributor": "ai-generated"
  },
  {
    "id": "boundaries-009",
    "category": "relationship_dynamics",
    "text": "Sağlıklı ilişkilerin net sınırlara ihtiyacı olduğunu düşünüyorum.",
    "answer_type": "likert",
    "scale_low_label": "kesinlikle katılmıyorum",
    "scale_high_label": "kesinlikle katılıyorum",
    "options": null,
    "depth": "light",
    "weight": "reflective",
    "spice": 0,
    "language": "tr",
    "tags": ["boundaries", "values"],
    "status": "draft",
    "created_at": "2026-05-24T00:00:00Z",
    "updated_at": "2026-05-24T00:00:00Z",
    "contributor": "ai-generated"
  },
  {
    "id": "boundaries-010",
    "category": "relationship_dynamics",
    "text": "Başkalarının sorunlarını kendi sorunummuş gibi üstüme alma eğilimim var.",
    "answer_type": "likert",
    "scale_low_label": "kesinlikle katılmıyorum",
    "scale_high_label": "kesinlikle katılıyorum",
    "options": null,
    "depth": "deep",
    "weight": "revealing",
    "spice": 0,
    "language": "tr",
    "tags": ["boundaries", "self_perception"],
    "status": "draft",
    "created_at": "2026-05-24T00:00:00Z",
    "updated_at": "2026-05-24T00:00:00Z",
    "contributor": "ai-generated"
  },
  {
    "id": "boundaries-011",
    "category": "relationship_dynamics",
    "text": "Dengede hissetmek için ne kadar yalnız zamana ihtiyacım var?",
    "answer_type": "multiple_choice",
    "scale_low_label": null,
    "scale_high_label": null,
    "options": [
      "Çok fazla",
      "Epeyce",
      "Birazcık",
      "Neredeyse hiç",
      "Ruh halime göre değişir"
    ],
    "depth": "light",
    "weight": "reflective",
    "spice": 0,
    "language": "tr",
    "tags": ["boundaries", "social_energy"],
    "status": "draft",
    "created_at": "2026-05-24T00:00:00Z",
    "updated_at": "2026-05-24T00:00:00Z",
    "contributor": "ai-generated"
  },
  {
    "id": "boundaries-012",
    "category": "relationship_dynamics",
    "text": "Bir ilişkide benim için en önemli olan sınır hangisi?",
    "answer_type": "multiple_choice",
    "scale_low_label": null,
    "scale_high_label": null,
    "options": [
      "Kişisel alan ve zaman",
      "Mahremiyet",
      "Tartışmada saygı",
      "Kendi arkadaşlıklarımı koruyabilmek",
      "Maddi bağımsızlık"
    ],
    "depth": "deep",
    "weight": "revealing",
    "spice": 0,
    "language": "tr",
    "tags": ["boundaries", "values"],
    "status": "draft",
    "created_at": "2026-05-24T00:00:00Z",
    "updated_at": "2026-05-24T00:00:00Z",
    "contributor": "ai-generated"
  },
  {
    "id": "boundaries-013",
    "category": "relationship_dynamics",
    "text": "Sınır koymak benim için ne kadar kolay?",
    "answer_type": "multiple_choice",
    "scale_low_label": null,
    "scale_high_label": null,
    "options": [
      "Kolay ve net",
      "Biraz çabayla",
      "Gerçekten zor",
      "Ancak çok zorlanırsam",
      "Pek beceremem"
    ],
    "depth": "deep",
    "weight": "revealing",
    "spice": 0,
    "language": "tr",
    "tags": ["boundaries", "self_perception"],
    "status": "draft",
    "created_at": "2026-05-24T00:00:00Z",
    "updated_at": "2026-05-24T00:00:00Z",
    "contributor": "ai-generated"
  },
  {
    "id": "boundaries-014",
    "category": "relationship_dynamics",
    "text": "Biri sınırımı aştığında nasıl tepki veririm?",
    "answer_type": "multiple_choice",
    "scale_low_label": null,
    "scale_high_label": null,
    "options": [
      "Doğrudan dile getiririm",
      "Görmezden gelirim ama incinirim",
      "Sessizce geri çekilirim",
      "Sinirlenirim",
      "Kim olduğuna bağlı"
    ],
    "depth": "deep",
    "weight": "revealing",
    "spice": 0,
    "language": "tr",
    "tags": ["boundaries", "conflict"],
    "status": "draft",
    "created_at": "2026-05-24T00:00:00Z",
    "updated_at": "2026-05-24T00:00:00Z",
    "contributor": "ai-generated"
  },
  {
    "id": "boundaries-015",
    "category": "relationship_dynamics",
    "text": "Sınır korumak bana en çok nerede zor geliyor?",
    "answer_type": "multiple_choice",
    "scale_low_label": null,
    "scale_high_label": null,
    "options": [
      "Aileyle",
      "Partnerimle",
      "İşte",
      "Arkadaşlarla",
      "Herkesle aynı ölçüde"
    ],
    "depth": "deep",
    "weight": "revealing",
    "spice": 0,
    "language": "tr",
    "tags": ["boundaries", "self_perception"],
    "status": "draft",
    "created_at": "2026-05-24T00:00:00Z",
    "updated_at": "2026-05-24T00:00:00Z",
    "contributor": "ai-generated"
  },
  {
    "id": "boundaries-016",
    "category": "relationship_dynamics",
    "text": "Hayır demek bana kolay geliyor mu?",
    "answer_type": "binary",
    "scale_low_label": null,
    "scale_high_label": null,
    "options": ["Evet", "Hayır"],
    "depth": "deep",
    "weight": "revealing",
    "spice": 0,
    "language": "tr",
    "tags": ["boundaries", "communication"],
    "status": "draft",
    "created_at": "2026-05-24T00:00:00Z",
    "updated_at": "2026-05-24T00:00:00Z",
    "contributor": "ai-generated"
  },
  {
    "id": "boundaries-017",
    "category": "relationship_dynamics",
    "text": "Partnerimden daha çok kişisel alana ihtiyacım var mı?",
    "answer_type": "binary",
    "scale_low_label": null,
    "scale_high_label": null,
    "options": ["Evet", "Hayır"],
    "depth": "deep",
    "weight": "revealing",
    "spice": 0,
    "language": "tr",
    "tags": ["boundaries", "social_energy"],
    "status": "draft",
    "created_at": "2026-05-24T00:00:00Z",
    "updated_at": "2026-05-24T00:00:00Z",
    "contributor": "ai-generated"
  },
  {
    "id": "boundaries-018",
    "category": "relationship_dynamics",
    "text": "Kendimi biraz insanları memnun etmeye çalışan biri olarak görüyor muyum?",
    "answer_type": "binary",
    "scale_low_label": null,
    "scale_high_label": null,
    "options": ["Evet", "Hayır"],
    "depth": "deep",
    "weight": "revealing",
    "spice": 0,
    "language": "tr",
    "tags": ["boundaries", "self_perception"],
    "status": "draft",
    "created_at": "2026-05-24T00:00:00Z",
    "updated_at": "2026-05-24T00:00:00Z",
    "contributor": "ai-generated"
  },
  {
    "id": "boundaries-019",
    "category": "relationship_dynamics",
    "text": "İhtiyacım olan ama istemekte zorlandığım bir sınır nedir?",
    "answer_type": "free_text",
    "scale_low_label": null,
    "scale_high_label": null,
    "options": null,
    "depth": "vulnerable",
    "weight": "revealing",
    "spice": 0,
    "language": "tr",
    "tags": ["boundaries", "communication"],
    "status": "draft",
    "created_at": "2026-05-24T00:00:00Z",
    "updated_at": "2026-05-24T00:00:00Z",
    "contributor": "ai-generated"
  },
  {
    "id": "boundaries-020",
    "category": "relationship_dynamics",
    "text": "Sınırlarıma saygı duyulduğunu hissetmemi ne sağlar?",
    "answer_type": "free_text",
    "scale_low_label": null,
    "scale_high_label": null,
    "options": null,
    "depth": "deep",
    "weight": "revealing",
    "spice": 0,
    "language": "tr",
    "tags": ["boundaries", "feeling_loved"],
    "status": "draft",
    "created_at": "2026-05-24T00:00:00Z",
    "updated_at": "2026-05-24T00:00:00Z",
    "contributor": "ai-generated"
  },
  {
    "id": "roles_responsibility-001",
    "category": "relationship_dynamics",
    "text": "Ev sorumluluklarının eşit paylaşılması gerektiğine inanıyorum.",
    "answer_type": "likert",
    "scale_low_label": "kesinlikle katılmıyorum",
    "scale_high_label": "kesinlikle katılıyorum",
    "options": null,
    "depth": "light",
    "weight": "reflective",
    "spice": 0,
    "language": "tr",
    "tags": ["roles", "household_chores", "values"],
    "status": "draft",
    "created_at": "2026-05-24T00:00:00Z",
    "updated_at": "2026-05-24T00:00:00Z",
    "contributor": "ai-generated"
  },
  {
    "id": "roles_responsibility-002",
    "category": "relationship_dynamics",
    "text": "Bir şeyin yapılması gerektiğinde inisiyatif alan genelde ben olurum.",
    "answer_type": "likert",
    "scale_low_label": "kesinlikle katılmıyorum",
    "scale_high_label": "kesinlikle katılıyorum",
    "options": null,
    "depth": "light",
    "weight": "reflective",
    "spice": 0,
    "language": "tr",
    "tags": ["roles", "self_perception"],
    "status": "draft",
    "created_at": "2026-05-24T00:00:00Z",
    "updated_at": "2026-05-24T00:00:00Z",
    "contributor": "ai-generated"
  },
  {
    "id": "roles_responsibility-003",
    "category": "relationship_dynamics",
    "text": "Zihinsel yükün partnerimin farkında olduğundan daha fazlasını taşıyorum.",
    "answer_type": "likert",
    "scale_low_label": "kesinlikle katılmıyorum",
    "scale_high_label": "kesinlikle katılıyorum",
    "options": null,
    "depth": "deep",
    "weight": "revealing",
    "spice": 0,
    "language": "tr",
    "tags": ["roles", "feeling_hurt"],
    "status": "draft",
    "created_at": "2026-05-24T00:00:00Z",
    "updated_at": "2026-05-24T00:00:00Z",
    "contributor": "ai-generated"
  },
  {
    "id": "roles_responsibility-004",
    "category": "relationship_dynamics",
    "text": "Büyük kararlarda partnerimin liderlik etmesinden rahatsız olmam.",
    "answer_type": "likert",
    "scale_low_label": "kesinlikle katılmıyorum",
    "scale_high_label": "kesinlikle katılıyorum",
    "options": null,
    "depth": "deep",
    "weight": "revealing",
    "spice": 0,
    "language": "tr",
    "tags": ["roles", "decisions"],
    "status": "draft",
    "created_at": "2026-05-24T00:00:00Z",
    "updated_at": "2026-05-24T00:00:00Z",
    "contributor": "ai-generated"
  },
  {
    "id": "roles_responsibility-005",
    "category": "relationship_dynamics",
    "text": "İlişkideki rollerin geleneklere değil, kişinin güçlü yönlerine göre belirlenmesi gerektiğini düşünüyorum.",
    "answer_type": "likert",
    "scale_low_label": "kesinlikle katılmıyorum",
    "scale_high_label": "kesinlikle katılıyorum",
    "options": null,
    "depth": "deep",
    "weight": "revealing",
    "spice": 0,
    "language": "tr",
    "tags": ["roles", "values"],
    "status": "draft",
    "created_at": "2026-05-24T00:00:00Z",
    "updated_at": "2026-05-24T00:00:00Z",
    "contributor": "ai-generated"
  },
  {
    "id": "roles_responsibility-006",
    "category": "relationship_dynamics",
    "text": "Bize uyuyorsa evi geçindiren ana kişi olmaktan mutluluk duyarım.",
    "answer_type": "likert",
    "scale_low_label": "kesinlikle katılmıyorum",
    "scale_high_label": "kesinlikle katılıyorum",
    "options": null,
    "depth": "deep",
    "weight": "revealing",
    "spice": 0,
    "language": "tr",
    "tags": ["roles", "money", "values"],
    "status": "draft",
    "created_at": "2026-05-24T00:00:00Z",
    "updated_at": "2026-05-24T00:00:00Z",
    "contributor": "ai-generated"
  },
  {
    "id": "roles_responsibility-007",
    "category": "relationship_dynamics",
    "text": "Evin düzenini sağlayan kişi olmaktan memnun olurum.",
    "answer_type": "likert",
    "scale_low_label": "kesinlikle katılmıyorum",
    "scale_high_label": "kesinlikle katılıyorum",
    "options": null,
    "depth": "deep",
    "weight": "revealing",
    "spice": 0,
    "language": "tr",
    "tags": ["roles", "household_chores", "values"],
    "status": "draft",
    "created_at": "2026-05-24T00:00:00Z",
    "updated_at": "2026-05-24T00:00:00Z",
    "contributor": "ai-generated"
  },
  {
    "id": "roles_responsibility-008",
    "category": "relationship_dynamics",
    "text": "Her birimizin net rolleri olan bir ilişkiyi tercih ederim.",
    "answer_type": "likert",
    "scale_low_label": "kesinlikle katılmıyorum",
    "scale_high_label": "kesinlikle katılıyorum",
    "options": null,
    "depth": "deep",
    "weight": "revealing",
    "spice": 0,
    "language": "tr",
    "tags": ["roles", "values"],
    "status": "draft",
    "created_at": "2026-05-24T00:00:00Z",
    "updated_at": "2026-05-24T00:00:00Z",
    "contributor": "ai-generated"
  },
  {
    "id": "roles_responsibility-009",
    "category": "relationship_dynamics",
    "text": "Aramızdaki iş bölümünün adil olduğunu düşünüyorum.",
    "answer_type": "likert",
    "scale_low_label": "kesinlikle katılmıyorum",
    "scale_high_label": "kesinlikle katılıyorum",
    "options": null,
    "depth": "deep",
    "weight": "revealing",
    "spice": 0,
    "language": "tr",
    "tags": ["roles", "household_chores"],
    "status": "draft",
    "created_at": "2026-05-24T00:00:00Z",
    "updated_at": "2026-05-24T00:00:00Z",
    "contributor": "ai-generated"
  },
  {
    "id": "roles_responsibility-010",
    "category": "relationship_dynamics",
    "text": "Evdeki işin çok daha fazlasını yapar duruma gelirsem buna içerlerim.",
    "answer_type": "likert",
    "scale_low_label": "kesinlikle katılmıyorum",
    "scale_high_label": "kesinlikle katılıyorum",
    "options": null,
    "depth": "deep",
    "weight": "revealing",
    "spice": 0,
    "language": "tr",
    "tags": ["roles", "household_chores", "conflict"],
    "status": "draft",
    "created_at": "2026-05-24T00:00:00Z",
    "updated_at": "2026-05-24T00:00:00Z",
    "contributor": "ai-generated"
  },
  {
    "id": "roles_responsibility-011",
    "category": "relationship_dynamics",
    "text": "Bir ortaklıkta en doğal olarak hangi rolü üstlenirim?",
    "answer_type": "multiple_choice",
    "scale_low_label": null,
    "scale_high_label": null,
    "options": [
      "Planlayan",
      "Geçindiren",
      "Bakım veren",
      "Arabulucu",
      "Destekleyen"
    ],
    "depth": "deep",
    "weight": "revealing",
    "spice": 0,
    "language": "tr",
    "tags": ["roles", "self_perception"],
    "status": "draft",
    "created_at": "2026-05-24T00:00:00Z",
    "updated_at": "2026-05-24T00:00:00Z",
    "contributor": "ai-generated"
  },
  {
    "id": "roles_responsibility-012",
    "category": "relationship_dynamics",
    "text": "Sorumluluklar bence nasıl paylaşılmalı?",
    "answer_type": "multiple_choice",
    "scale_low_label": null,
    "scale_high_label": null,
    "options": [
      "Yarı yarıya",
      "Kim hangisinde daha iyiyse",
      "Kimin daha fazla vakti varsa",
      "Esnek, haftadan haftaya",
      "Geleneksel çizgilerde"
    ],
    "depth": "deep",
    "weight": "revealing",
    "spice": 0,
    "language": "tr",
    "tags": ["roles", "values"],
    "status": "draft",
    "created_at": "2026-05-24T00:00:00Z",
    "updated_at": "2026-05-24T00:00:00Z",
    "contributor": "ai-generated"
  },
  {
    "id": "roles_responsibility-013",
    "category": "relationship_dynamics",
    "text": "Bir ilişkide en çok hangi sorumluluğu üstlenmek isterim?",
    "answer_type": "multiple_choice",
    "scale_low_label": null,
    "scale_high_label": null,
    "options": [
      "Maddi işler",
      "Yemek ve ev düzeni",
      "Planlama ve organizasyon",
      "Duygusal destek",
      "Geliri kazanmak"
    ],
    "depth": "deep",
    "weight": "revealing",
    "spice": 0,
    "language": "tr",
    "tags": ["roles", "values"],
    "status": "draft",
    "created_at": "2026-05-24T00:00:00Z",
    "updated_at": "2026-05-24T00:00:00Z",
    "contributor": "ai-generated"
  },
  {
    "id": "roles_responsibility-014",
    "category": "relationship_dynamics",
    "text": "Hangi sorumluluğu seve seve devrederdim?",
    "answer_type": "multiple_choice",
    "scale_low_label": null,
    "scale_high_label": null,
    "options": [
      "Para yönetimi",
      "Yemek",
      "Temizlik",
      "Planlama ve idari işler",
      "Açıkçası hiçbirini"
    ],
    "depth": "light",
    "weight": "playful",
    "spice": 0,
    "language": "tr",
    "tags": ["roles", "household_chores"],
    "status": "draft",
    "created_at": "2026-05-24T00:00:00Z",
    "updated_at": "2026-05-24T00:00:00Z",
    "contributor": "ai-generated"
  },
  {
    "id": "roles_responsibility-015",
    "category": "relationship_dynamics",
    "text": "İlişkideki roller konusundaki görüşlerimi en çok ne şekillendirdi?",
    "answer_type": "multiple_choice",
    "scale_low_label": null,
    "scale_high_label": null,
    "options": [
      "Annem babamın yapma biçimi",
      "Kendi inançlarım",
      "Geçmiş ilişkilerim",
      "Bana adil gelen şey",
      "Kültürüm"
    ],
    "depth": "deep",
    "weight": "revealing",
    "spice": 0,
    "language": "tr",
    "tags": ["roles", "formative", "family"],
    "status": "draft",
    "created_at": "2026-05-24T00:00:00Z",
    "updated_at": "2026-05-24T00:00:00Z",
    "contributor": "ai-generated"
  },
  {
    "id": "roles_responsibility-016",
    "category": "relationship_dynamics",
    "text": "Kararlarda daha çok lider miyim yoksa destekleyen mi?",
    "answer_type": "binary",
    "scale_low_label": null,
    "scale_high_label": null,
    "options": ["Lider", "Destekleyen"],
    "depth": "deep",
    "weight": "revealing",
    "spice": 0,
    "language": "tr",
    "tags": ["roles", "self_perception"],
    "status": "draft",
    "created_at": "2026-05-24T00:00:00Z",
    "updated_at": "2026-05-24T00:00:00Z",
    "contributor": "ai-generated"
  },
  {
    "id": "roles_responsibility-017",
    "category": "relationship_dynamics",
    "text": "Modern ilişkilerde geleneksel cinsiyet rollerinin yeri olduğunu düşünüyor muyum?",
    "answer_type": "binary",
    "scale_low_label": null,
    "scale_high_label": null,
    "options": ["Evet", "Hayır"],
    "depth": "deep",
    "weight": "revealing",
    "spice": 0,
    "language": "tr",
    "tags": ["roles", "values"],
    "status": "draft",
    "created_at": "2026-05-24T00:00:00Z",
    "updated_at": "2026-05-24T00:00:00Z",
    "contributor": "ai-generated"
  },
  {
    "id": "roles_responsibility-018",
    "category": "relationship_dynamics",
    "text": "Ortak sorumluluklarda üzerime düşeni yaptığımı hissediyor muyum?",
    "answer_type": "binary",
    "scale_low_label": null,
    "scale_high_label": null,
    "options": ["Evet", "Hayır"],
    "depth": "deep",
    "weight": "revealing",
    "spice": 0,
    "language": "tr",
    "tags": ["roles", "self_perception"],
    "status": "draft",
    "created_at": "2026-05-24T00:00:00Z",
    "updated_at": "2026-05-24T00:00:00Z",
    "contributor": "ai-generated"
  },
  {
    "id": "roles_responsibility-019",
    "category": "relationship_dynamics",
    "text": "Hayattaki sorumlulukların adil paylaşımı benim için nasıl görünür?",
    "answer_type": "free_text",
    "scale_low_label": null,
    "scale_high_label": null,
    "options": null,
    "depth": "deep",
    "weight": "revealing",
    "spice": 0,
    "language": "tr",
    "tags": ["roles", "values"],
    "status": "draft",
    "created_at": "2026-05-24T00:00:00Z",
    "updated_at": "2026-05-24T00:00:00Z",
    "contributor": "ai-generated"
  },
  {
    "id": "roles_responsibility-020",
    "category": "relationship_dynamics",
    "text": "Daha fazla yardım ya da takdir görmek istediğim bir sorumluluk hangisi?",
    "answer_type": "free_text",
    "scale_low_label": null,
    "scale_high_label": null,
    "options": null,
    "depth": "deep",
    "weight": "revealing",
    "spice": 0,
    "language": "tr",
    "tags": ["roles", "communication", "feeling_hurt"],
    "status": "draft",
    "created_at": "2026-05-24T00:00:00Z",
    "updated_at": "2026-05-24T00:00:00Z",
    "contributor": "ai-generated"
  },
  {
    "id": "social_energy-001",
    "category": "social_world",
    "text": "İnsanların arasında olmak beni yormaktan çok enerji veriyor.",
    "answer_type": "likert",
    "scale_low_label": "kesinlikle katılmıyorum",
    "scale_high_label": "kesinlikle katılıyorum",
    "options": null,
    "depth": "light",
    "weight": "reflective",
    "spice": 0,
    "language": "tr",
    "tags": ["social_energy", "self_perception"],
    "status": "draft",
    "created_at": "2026-05-24T00:00:00Z",
    "updated_at": "2026-05-24T00:00:00Z",
    "contributor": "ai-generated"
  },
  {
    "id": "social_energy-002",
    "category": "social_world",
    "text": "Sosyalleştikten sonra kendime gelmek için sessiz, yalnız bir zamana ihtiyacım var.",
    "answer_type": "likert",
    "scale_low_label": "kesinlikle katılmıyorum",
    "scale_high_label": "kesinlikle katılıyorum",
    "options": null,
    "depth": "light",
    "weight": "reflective",
    "spice": 0,
    "language": "tr",
    "tags": ["social_energy", "self_perception"],
    "status": "draft",
    "created_at": "2026-05-24T00:00:00Z",
    "updated_at": "2026-05-24T00:00:00Z",
    "contributor": "ai-generated"
  },
  {
    "id": "social_energy-003",
    "category": "social_world",
    "text": "Büyük buluşmalardan ve partilerden keyif alırım.",
    "answer_type": "likert",
    "scale_low_label": "kesinlikle katılmıyorum",
    "scale_high_label": "kesinlikle katılıyorum",
    "options": null,
    "depth": "icebreaker",
    "weight": "playful",
    "spice": 0,
    "language": "tr",
    "tags": ["social_energy", "tastes"],
    "status": "draft",
    "created_at": "2026-05-24T00:00:00Z",
    "updated_at": "2026-05-24T00:00:00Z",
    "contributor": "ai-generated"
  },
  {
    "id": "social_energy-004",
    "category": "social_world",
    "text": "Yüzeysel konuşmalar yerine birkaç derin sohbet etmeyi tercih ederim.",
    "answer_type": "likert",
    "scale_low_label": "kesinlikle katılmıyorum",
    "scale_high_label": "kesinlikle katılıyorum",
    "options": null,
    "depth": "light",
    "weight": "reflective",
    "spice": 0,
    "language": "tr",
    "tags": ["social_energy", "communication"],
    "status": "draft",
    "created_at": "2026-05-24T00:00:00Z",
    "updated_at": "2026-05-24T00:00:00Z",
    "contributor": "ai-generated"
  },
  {
    "id": "social_energy-005",
    "category": "social_world",
    "text": "Kimseyi tanımadığım bir mekana girmek beni rahatsız etmez.",
    "answer_type": "likert",
    "scale_low_label": "kesinlikle katılmıyorum",
    "scale_high_label": "kesinlikle katılıyorum",
    "options": null,
    "depth": "light",
    "weight": "reflective",
    "spice": 0,
    "language": "tr",
    "tags": ["social_energy", "confidence"],
    "status": "draft",
    "created_at": "2026-05-24T00:00:00Z",
    "updated_at": "2026-05-24T00:00:00Z",
    "contributor": "ai-generated"
  },
  {
    "id": "social_energy-006",
    "category": "social_world",
    "text": "İnsanların arasındayken bile sık sık yalnız hissediyorum.",
    "answer_type": "likert",
    "scale_low_label": "kesinlikle katılmıyorum",
    "scale_high_label": "kesinlikle katılıyorum",
    "options": null,
    "depth": "vulnerable",
    "weight": "revealing",
    "spice": 0,
    "language": "tr",
    "tags": ["social_energy", "feelings"],
    "status": "draft",
    "created_at": "2026-05-24T00:00:00Z",
    "updated_at": "2026-05-24T00:00:00Z",
    "contributor": "ai-generated"
  },
  {
    "id": "social_energy-007",
    "category": "social_world",
    "text": "Planı olmayan boş bir akşamı dört gözle beklerim.",
    "answer_type": "likert",
    "scale_low_label": "kesinlikle katılmıyorum",
    "scale_high_label": "kesinlikle katılıyorum",
    "options": null,
    "depth": "light",
    "weight": "playful",
    "spice": 0,
    "language": "tr",
    "tags": ["social_energy", "tastes"],
    "status": "draft",
    "created_at": "2026-05-24T00:00:00Z",
    "updated_at": "2026-05-24T00:00:00Z",
    "contributor": "ai-generated"
  },
  {
    "id": "social_energy-008",
    "category": "social_world",
    "text": "Grubun enerjisini yüksek tutan kişi genelde benim.",
    "answer_type": "likert",
    "scale_low_label": "kesinlikle katılmıyorum",
    "scale_high_label": "kesinlikle katılıyorum",
    "options": null,
    "depth": "light",
    "weight": "reflective",
    "spice": 0,
    "language": "tr",
    "tags": ["social_energy", "group_behavior"],
    "status": "draft",
    "created_at": "2026-05-24T00:00:00Z",
    "updated_at": "2026-05-24T00:00:00Z",
    "contributor": "ai-generated"
  },
  {
    "id": "social_energy-009",
    "category": "social_world",
    "text": "Fazla sosyalleşmek beni boğulmuş hissettiriyor.",
    "answer_type": "likert",
    "scale_low_label": "kesinlikle katılmıyorum",
    "scale_high_label": "kesinlikle katılıyorum",
    "options": null,
    "depth": "light",
    "weight": "reflective",
    "spice": 0,
    "language": "tr",
    "tags": ["social_energy", "stress"],
    "status": "draft",
    "created_at": "2026-05-24T00:00:00Z",
    "updated_at": "2026-05-24T00:00:00Z",
    "contributor": "ai-generated"
  },
  {
    "id": "social_energy-010",
    "category": "social_world",
    "text": "Önceden haberim olmasa bile sosyal etkinliklere takılmaktan memnun olurum.",
    "answer_type": "likert",
    "scale_low_label": "kesinlikle katılmıyorum",
    "scale_high_label": "kesinlikle katılıyorum",
    "options": null,
    "depth": "light",
    "weight": "playful",
    "spice": 0,
    "language": "tr",
    "tags": ["social_energy", "self_perception"],
    "status": "draft",
    "created_at": "2026-05-24T00:00:00Z",
    "updated_at": "2026-05-24T00:00:00Z",
    "contributor": "ai-generated"
  },
  {
    "id": "social_energy-011",
    "category": "social_world",
    "text": "İçedönük-dışadönük ölçeğinde nerede duruyorum?",
    "answer_type": "multiple_choice",
    "scale_low_label": null,
    "scale_high_label": null,
    "options": [
      "Tamamen içedönük",
      "İçedönüğe yakın",
      "Tam ortada",
      "Dışadönüğe yakın",
      "Tamamen dışadönük"
    ],
    "depth": "light",
    "weight": "reflective",
    "spice": 0,
    "language": "tr",
    "tags": ["social_energy", "self_perception"],
    "status": "draft",
    "created_at": "2026-05-24T00:00:00Z",
    "updated_at": "2026-05-24T00:00:00Z",
    "contributor": "ai-generated"
  },
  {
    "id": "social_energy-012",
    "category": "social_world",
    "text": "Cuma akşamımı geçirmenin ideal yolu nedir?",
    "answer_type": "multiple_choice",
    "scale_low_label": null,
    "scale_high_label": null,
    "options": [
      "Hareketli bir gece",
      "Birkaç arkadaşla yemek",
      "Sessiz bir ev akşamı",
      "Sadece ben ve partnerim",
      "Anlık gelişen bir şey"
    ],
    "depth": "light",
    "weight": "playful",
    "spice": 0,
    "language": "tr",
    "tags": ["social_energy", "tastes"],
    "status": "draft",
    "created_at": "2026-05-24T00:00:00Z",
    "updated_at": "2026-05-24T00:00:00Z",
    "contributor": "ai-generated"
  },
  {
    "id": "social_energy-013",
    "category": "social_world",
    "text": "Yorucu bir haftanın ardından genelde nasıl kendime gelirim?",
    "answer_type": "multiple_choice",
    "scale_low_label": null,
    "scale_high_label": null,
    "options": [
      "Yalnız zaman",
      "Yakınlarımla vakit",
      "Doğaya çıkmak",
      "Hiçbir şey yapmamak",
      "Eğlenceli bir sosyal etkinlik"
    ],
    "depth": "light",
    "weight": "reflective",
    "spice": 0,
    "language": "tr",
    "tags": ["social_energy", "coping"],
    "status": "draft",
    "created_at": "2026-05-24T00:00:00Z",
    "updated_at": "2026-05-24T00:00:00Z",
    "contributor": "ai-generated"
  },
  {
    "id": "social_energy-014",
    "category": "social_world",
    "text": "Kimseyi pek tanımadığım bir partide genelde nasıl hissederim?",
    "answer_type": "multiple_choice",
    "scale_low_label": null,
    "scale_high_label": null,
    "options": [
      "Enerji dolu",
      "Meraklı ama temkinli",
      "Biraz tedirgin",
      "Çabuk yorgun",
      "Erken çıkmaya hazır"
    ],
    "depth": "light",
    "weight": "reflective",
    "spice": 0,
    "language": "tr",
    "tags": ["social_energy", "social_behavior"],
    "status": "draft",
    "created_at": "2026-05-24T00:00:00Z",
    "updated_at": "2026-05-24T00:00:00Z",
    "contributor": "ai-generated"
  },
  {
    "id": "social_energy-015",
    "category": "social_world",
    "text": "Tipik bir haftada ne sıklıkla sosyalleşmek isterim?",
    "answer_type": "multiple_choice",
    "scale_low_label": null,
    "scale_high_label": null,
    "options": [
      "Neredeyse her gün",
      "Birkaç kez",
      "Bir iki kez",
      "Nadiren",
      "Gerçekten değişir"
    ],
    "depth": "light",
    "weight": "reflective",
    "spice": 0,
    "language": "tr",
    "tags": ["social_energy", "habits"],
    "status": "draft",
    "created_at": "2026-05-24T00:00:00Z",
    "updated_at": "2026-05-24T00:00:00Z",
    "contributor": "ai-generated"
  },
  {
    "id": "social_energy-016",
    "category": "social_world",
    "text": "Yalnız olmaktan mı yoksa başkalarıyla olmaktan mı daha çok enerji alırım?",
    "answer_type": "binary",
    "scale_low_label": null,
    "scale_high_label": null,
    "options": ["Yalnız olmaktan", "Başkalarıyla olmaktan"],
    "depth": "light",
    "weight": "reflective",
    "spice": 0,
    "language": "tr",
    "tags": ["social_energy", "self_perception"],
    "status": "draft",
    "created_at": "2026-05-24T00:00:00Z",
    "updated_at": "2026-05-24T00:00:00Z",
    "contributor": "ai-generated"
  },
  {
    "id": "social_energy-017",
    "category": "social_world",
    "text": "Sosyal planları organize eden kişi genelde ben miyim?",
    "answer_type": "binary",
    "scale_low_label": null,
    "scale_high_label": null,
    "options": ["Evet", "Hayır"],
    "depth": "light",
    "weight": "reflective",
    "spice": 0,
    "language": "tr",
    "tags": ["social_energy", "group_behavior"],
    "status": "draft",
    "created_at": "2026-05-24T00:00:00Z",
    "updated_at": "2026-05-24T00:00:00Z",
    "contributor": "ai-generated"
  },
  {
    "id": "social_energy-018",
    "category": "social_world",
    "text": "Bazen evde kalmayı tercih ettiğim için planları iptal eder miyim?",
    "answer_type": "binary",
    "scale_low_label": null,
    "scale_high_label": null,
    "options": ["Evet", "Hayır"],
    "depth": "light",
    "weight": "playful",
    "spice": 0,
    "language": "tr",
    "tags": ["social_energy", "habits"],
    "status": "draft",
    "created_at": "2026-05-24T00:00:00Z",
    "updated_at": "2026-05-24T00:00:00Z",
    "contributor": "ai-generated"
  },
  {
    "id": "social_energy-019",
    "category": "social_world",
    "text": "Hangi sosyal ortam içimdeki en iyi yanı ortaya çıkarır?",
    "answer_type": "free_text",
    "scale_low_label": null,
    "scale_high_label": null,
    "options": null,
    "depth": "light",
    "weight": "reflective",
    "spice": 0,
    "language": "tr",
    "tags": ["social_energy", "self_perception"],
    "status": "draft",
    "created_at": "2026-05-24T00:00:00Z",
    "updated_at": "2026-05-24T00:00:00Z",
    "contributor": "ai-generated"
  },
  {
    "id": "social_energy-020",
    "category": "social_world",
    "text": "Partnerimin sosyal ihtiyaçlarımı daha iyi anlamasını nasıl isterdim?",
    "answer_type": "free_text",
    "scale_low_label": null,
    "scale_high_label": null,
    "options": null,
    "depth": "deep",
    "weight": "revealing",
    "spice": 0,
    "language": "tr",
    "tags": ["social_energy", "communication", "boundaries"],
    "status": "draft",
    "created_at": "2026-05-24T00:00:00Z",
    "updated_at": "2026-05-24T00:00:00Z",
    "contributor": "ai-generated"
  },
  {
    "id": "friendships-001",
    "category": "social_world",
    "text": "Arkadaşlıklarım, hayatımın en önemli parçalarından biri.",
    "answer_type": "likert",
    "scale_low_label": "kesinlikle katılmıyorum",
    "scale_high_label": "kesinlikle katılıyorum",
    "options": null,
    "depth": "light",
    "weight": "reflective",
    "spice": 0,
    "language": "tr",
    "tags": ["friendships", "values"],
    "status": "draft",
    "created_at": "2026-05-24T00:00:00Z",
    "updated_at": "2026-05-24T00:00:00Z",
    "contributor": "ai-generated"
  },
  {
    "id": "friendships-002",
    "category": "social_world",
    "text": "Geniş bir çevre yerine birkaç yakın arkadaşımın olmasını tercih ederim.",
    "answer_type": "likert",
    "scale_low_label": "kesinlikle katılmıyorum",
    "scale_high_label": "kesinlikle katılıyorum",
    "options": null,
    "depth": "light",
    "weight": "reflective",
    "spice": 0,
    "language": "tr",
    "tags": ["friendships", "self_perception"],
    "status": "draft",
    "created_at": "2026-05-24T00:00:00Z",
    "updated_at": "2026-05-24T00:00:00Z",
    "contributor": "ai-generated"
  },
  {
    "id": "friendships-003",
    "category": "social_world",
    "text": "Başkalarının dertleriyle ilk başvurduğu arkadaş genelde benim.",
    "answer_type": "likert",
    "scale_low_label": "kesinlikle katılmıyorum",
    "scale_high_label": "kesinlikle katılıyorum",
    "options": null,
    "depth": "light",
    "weight": "reflective",
    "spice": 0,
    "language": "tr",
    "tags": ["friendships", "self_perception"],
    "status": "draft",
    "created_at": "2026-05-24T00:00:00Z",
    "updated_at": "2026-05-24T00:00:00Z",
    "contributor": "ai-generated"
  },
  {
    "id": "friendships-004",
    "category": "social_world",
    "text": "Yetişkin biri olarak yeni arkadaşlıklar kurmak bana kolay geliyor.",
    "answer_type": "likert",
    "scale_low_label": "kesinlikle katılmıyorum",
    "scale_high_label": "kesinlikle katılıyorum",
    "options": null,
    "depth": "light",
    "weight": "reflective",
    "spice": 0,
    "language": "tr",
    "tags": ["friendships", "social_energy"],
    "status": "draft",
    "created_at": "2026-05-24T00:00:00Z",
    "updated_at": "2026-05-24T00:00:00Z",
    "contributor": "ai-generated"
  },
  {
    "id": "friendships-005",
    "category": "social_world",
    "text": "Arkadaşlıklarımı canlı tutmak için çok çaba harcıyorum.",
    "answer_type": "likert",
    "scale_low_label": "kesinlikle katılmıyorum",
    "scale_high_label": "kesinlikle katılıyorum",
    "options": null,
    "depth": "deep",
    "weight": "revealing",
    "spice": 0,
    "language": "tr",
    "tags": ["friendships", "values"],
    "status": "draft",
    "created_at": "2026-05-24T00:00:00Z",
    "updated_at": "2026-05-24T00:00:00Z",
    "contributor": "ai-generated"
  },
  {
    "id": "friendships-006",
    "category": "social_world",
    "text": "Partnerimin arkadaşlarımla iyi geçinmesi benim için önemli.",
    "answer_type": "likert",
    "scale_low_label": "kesinlikle katılmıyorum",
    "scale_high_label": "kesinlikle katılıyorum",
    "options": null,
    "depth": "deep",
    "weight": "revealing",
    "spice": 0,
    "language": "tr",
    "tags": ["friendships", "values"],
    "status": "draft",
    "created_at": "2026-05-24T00:00:00Z",
    "updated_at": "2026-05-24T00:00:00Z",
    "contributor": "ai-generated"
  },
  {
    "id": "friendships-007",
    "category": "social_world",
    "text": "Sadece bana ait kalan bazı arkadaşlıklara ihtiyacım var.",
    "answer_type": "likert",
    "scale_low_label": "kesinlikle katılmıyorum",
    "scale_high_label": "kesinlikle katılıyorum",
    "options": null,
    "depth": "deep",
    "weight": "revealing",
    "spice": 0,
    "language": "tr",
    "tags": ["friendships", "boundaries"],
    "status": "draft",
    "created_at": "2026-05-24T00:00:00Z",
    "updated_at": "2026-05-24T00:00:00Z",
    "contributor": "ai-generated"
  },
  {
    "id": "friendships-008",
    "category": "social_world",
    "text": "Yakın kalmayı dilediğim ama uzaklaştığım arkadaşlarım oldu.",
    "answer_type": "likert",
    "scale_low_label": "kesinlikle katılmıyorum",
    "scale_high_label": "kesinlikle katılıyorum",
    "options": null,
    "depth": "deep",
    "weight": "revealing",
    "spice": 0,
    "language": "tr",
    "tags": ["friendships", "feelings"],
    "status": "draft",
    "created_at": "2026-05-24T00:00:00Z",
    "updated_at": "2026-05-24T00:00:00Z",
    "contributor": "ai-generated"
  },
  {
    "id": "friendships-009",
    "category": "social_world",
    "text": "Bir arkadaşta sadakate her şeyden çok değer veririm.",
    "answer_type": "likert",
    "scale_low_label": "kesinlikle katılmıyorum",
    "scale_high_label": "kesinlikle katılıyorum",
    "options": null,
    "depth": "deep",
    "weight": "revealing",
    "spice": 0,
    "language": "tr",
    "tags": ["friendships", "values"],
    "status": "draft",
    "created_at": "2026-05-24T00:00:00Z",
    "updated_at": "2026-05-24T00:00:00Z",
    "contributor": "ai-generated"
  },
  {
    "id": "friendships-010",
    "category": "social_world",
    "text": "Partnerim, herkesten önce benim en iyi arkadaşım olmalı.",
    "answer_type": "likert",
    "scale_low_label": "kesinlikle katılmıyorum",
    "scale_high_label": "kesinlikle katılıyorum",
    "options": null,
    "depth": "deep",
    "weight": "revealing",
    "spice": 0,
    "language": "tr",
    "tags": ["friendships", "values"],
    "status": "draft",
    "created_at": "2026-05-24T00:00:00Z",
    "updated_at": "2026-05-24T00:00:00Z",
    "contributor": "ai-generated"
  },
  {
    "id": "friendships-011",
    "category": "social_world",
    "text": "Bir arkadaşta en çok neye değer veririm?",
    "answer_type": "multiple_choice",
    "scale_low_label": null,
    "scale_high_label": null,
    "options": [
      "Sadakat",
      "Dürüstlük",
      "Eğlence ve kahkaha",
      "Zor zamanlarda yanımda olmak",
      "Kolay anlaşabilmek"
    ],
    "depth": "deep",
    "weight": "revealing",
    "spice": 0,
    "language": "tr",
    "tags": ["friendships", "values"],
    "status": "draft",
    "created_at": "2026-05-24T00:00:00Z",
    "updated_at": "2026-05-24T00:00:00Z",
    "contributor": "ai-generated"
  },
  {
    "id": "friendships-012",
    "category": "social_world",
    "text": "Arkadaş grubumda genelde hangi rolü üstlenirim?",
    "answer_type": "multiple_choice",
    "scale_low_label": null,
    "scale_high_label": null,
    "options": [
      "Organize eden",
      "Dinleyen",
      "Komik olan",
      "Akıl veren",
      "Sessiz ama sağlam olan"
    ],
    "depth": "light",
    "weight": "reflective",
    "spice": 0,
    "language": "tr",
    "tags": ["friendships", "self_perception"],
    "status": "draft",
    "created_at": "2026-05-24T00:00:00Z",
    "updated_at": "2026-05-24T00:00:00Z",
    "contributor": "ai-generated"
  },
  {
    "id": "friendships-013",
    "category": "social_world",
    "text": "Bugünlerde arkadaşlıklarım nasıl?",
    "answer_type": "multiple_choice",
    "scale_low_label": null,
    "scale_high_label": null,
    "options": [
      "Sıkı, yakın bir grup",
      "Birkaç dağınık yakın arkadaş",
      "Çok tanıdık ama az dost",
      "Çoğunlukla online",
      "İstediğimden daha az"
    ],
    "depth": "deep",
    "weight": "revealing",
    "spice": 0,
    "language": "tr",
    "tags": ["friendships", "self_perception"],
    "status": "draft",
    "created_at": "2026-05-24T00:00:00Z",
    "updated_at": "2026-05-24T00:00:00Z",
    "contributor": "ai-generated"
  },
  {
    "id": "friendships-014",
    "category": "social_world",
    "text": "Bir arkadaşlığı benim için ne bitirir?",
    "answer_type": "multiple_choice",
    "scale_low_label": null,
    "scale_high_label": null,
    "options": [
      "İhanet",
      "Birbirinden uzaklaşmak",
      "Tek taraflı çaba",
      "Yalan söylemek",
      "Doğal olarak savrulmak"
    ],
    "depth": "deep",
    "weight": "revealing",
    "spice": 0,
    "language": "tr",
    "tags": ["friendships", "boundaries"],
    "status": "draft",
    "created_at": "2026-05-24T00:00:00Z",
    "updated_at": "2026-05-24T00:00:00Z",
    "contributor": "ai-generated"
  },
  {
    "id": "friendships-015",
    "category": "social_world",
    "text": "Arkadaşlarımla bağlantıda kalmayı nasıl tercih ederim?",
    "answer_type": "multiple_choice",
    "scale_low_label": null,
    "scale_high_label": null,
    "options": [
      "Yüz yüze buluşarak",
      "Düzenli aramalarla",
      "Mesajlaşarak",
      "Grup sohbetleriyle",
      "Kaldığımız yerden devam ederek"
    ],
    "depth": "light",
    "weight": "reflective",
    "spice": 0,
    "language": "tr",
    "tags": ["friendships", "habits"],
    "status": "draft",
    "created_at": "2026-05-24T00:00:00Z",
    "updated_at": "2026-05-24T00:00:00Z",
    "contributor": "ai-generated"
  },
  {
    "id": "friendships-016",
    "category": "social_world",
    "text": "Gecenin bir yarısı arayabileceğim bir arkadaşım var mı?",
    "answer_type": "binary",
    "scale_low_label": null,
    "scale_high_label": null,
    "options": ["Evet", "Hayır"],
    "depth": "deep",
    "weight": "revealing",
    "spice": 0,
    "language": "tr",
    "tags": ["friendships", "trust"],
    "status": "draft",
    "created_at": "2026-05-24T00:00:00Z",
    "updated_at": "2026-05-24T00:00:00Z",
    "contributor": "ai-generated"
  },
  {
    "id": "friendships-017",
    "category": "social_world",
    "text": "Çocukluğumdan kalma arkadaşlarım hâlâ var mı?",
    "answer_type": "binary",
    "scale_low_label": null,
    "scale_high_label": null,
    "options": ["Evet", "Hayır"],
    "depth": "icebreaker",
    "weight": "playful",
    "spice": 0,
    "language": "tr",
    "tags": ["friendships", "childhood"],
    "status": "draft",
    "created_at": "2026-05-24T00:00:00Z",
    "updated_at": "2026-05-24T00:00:00Z",
    "contributor": "ai-generated"
  },
  {
    "id": "friendships-018",
    "category": "social_world",
    "text": "Şu anki halimden daha fazla yakın arkadaşımın olmasını ister miydim?",
    "answer_type": "binary",
    "scale_low_label": null,
    "scale_high_label": null,
    "options": ["Evet", "Hayır"],
    "depth": "vulnerable",
    "weight": "revealing",
    "spice": 0,
    "language": "tr",
    "tags": ["friendships", "feelings"],
    "status": "draft",
    "created_at": "2026-05-24T00:00:00Z",
    "updated_at": "2026-05-24T00:00:00Z",
    "contributor": "ai-generated"
  },
  {
    "id": "friendships-019",
    "category": "social_world",
    "text": "Beni şekillendiren bir arkadaşım var mı, varsa nasıl?",
    "answer_type": "free_text",
    "scale_low_label": null,
    "scale_high_label": null,
    "options": null,
    "depth": "deep",
    "weight": "revealing",
    "spice": 0,
    "language": "tr",
    "tags": ["friendships", "formative"],
    "status": "draft",
    "created_at": "2026-05-24T00:00:00Z",
    "updated_at": "2026-05-24T00:00:00Z",
    "contributor": "ai-generated"
  },
  {
    "id": "friendships-020",
    "category": "social_world",
    "text": "Başkaları için nasıl bir arkadaş olmayı umuyorum?",
    "answer_type": "free_text",
    "scale_low_label": null,
    "scale_high_label": null,
    "options": null,
    "depth": "deep",
    "weight": "revealing",
    "spice": 0,
    "language": "tr",
    "tags": ["friendships", "self_perception", "values"],
    "status": "draft",
    "created_at": "2026-05-24T00:00:00Z",
    "updated_at": "2026-05-24T00:00:00Z",
    "contributor": "ai-generated"
  }
]
